{"meta":{"loop":100000,"time":"20130116.175522"},"reports":{"fixture\/001-simple-vars-001.json":[{"lib":"handlebars.php","test":"fixture\/001-simple-vars-001.json","loop":100000,"time":35.301132917404,"match":"YES"},{"lib":"lightncandy","test":"fixture\/001-simple-vars-001.json","loop":100000,"time":2.0879209041595,"match":"YES"},{"lib":"mustache-php","test":"fixture\/001-simple-vars-001.json","loop":100000,"time":0,"match":"OUTPUT"},{"lib":"mustache.php","test":"fixture\/001-simple-vars-001.json","loop":100000,"time":8.2009260654449,"match":"YES"}],"fixture\/001-simple-vars-002.json":[{"lib":"handlebars.php","test":"fixture\/001-simple-vars-002.json","loop":100000,"time":0,"match":"OUTPUT"},{"lib":"lightncandy","test":"fixture\/001-simple-vars-002.json","loop":100000,"time":0,"match":"OUTPUT"},{"lib":"mustache-php","test":"fixture\/001-simple-vars-002.json","loop":100000,"time":0,"match":"OUTPUT"},{"lib":"mustache.php","test":"fixture\/001-simple-vars-002.json","loop":100000,"time":0,"match":"OUTPUT"}],"fixture\/001-simple-vars-003.json":[{"lib":"handlebars.php","test":"fixture\/001-simple-vars-003.json","loop":100000,"time":34.722861051559,"match":"YES"},{"lib":"lightncandy","test":"fixture\/001-simple-vars-003.json","loop":100000,"time":2.1335048675537,"match":"YES"},{"lib":"mustache-php","test":"fixture\/001-simple-vars-003.json","loop":100000,"time":0,"match":"OUTPUT"},{"lib":"mustache.php","test":"fixture\/001-simple-vars-003.json","loop":100000,"time":4.9229049682617,"match":"YES"}],"fixture\/001-simple-vars-004.json":[{"lib":"handlebars.php","test":"fixture\/001-simple-vars-004.json","loop":100000,"time":36.105829954147,"match":"YES"},{"lib":"lightncandy","test":"fixture\/001-simple-vars-004.json","loop":100000,"time":1.7753279209137,"match":"YES"},{"lib":"mustache-php","test":"fixture\/001-simple-vars-004.json","loop":100000,"time":0,"match":"OUTPUT"},{"lib":"mustache.php","test":"fixture\/001-simple-vars-004.json","loop":100000,"time":7.9130940437317,"match":"YES"}],"fixture\/001-simple-vars-005.json":[{"lib":"handlebars.php","test":"fixture\/001-simple-vars-005.json","loop":100000,"time":36.656342983246,"match":"YES"},{"lib":"lightncandy","test":"fixture\/001-simple-vars-005.json","loop":100000,"time":1.716315984726,"match":"YES"},{"lib":"mustache-php","test":"fixture\/001-simple-vars-005.json","loop":100000,"time":0,"match":"OUTPUT"},{"lib":"mustache.php","test":"fixture\/001-simple-vars-005.json","loop":100000,"time":7.8664360046387,"match":"YES"}],"fixture\/001-simple-vars-006.json":[{"lib":"handlebars.php","test":"fixture\/001-simple-vars-006.json","loop":100000,"time":0,"match":"OUTPUT"},{"lib":"lightncandy","test":"fixture\/001-simple-vars-006.json","loop":100000,"time":0,"match":"OUTPUT"},{"lib":"mustache-php","test":"fixture\/001-simple-vars-006.json","loop":100000,"time":0,"match":"OUTPUT"},{"lib":"mustache.php","test":"fixture\/001-simple-vars-006.json","loop":100000,"time":0,"match":"OUTPUT"}],"fixture\/002-simple-if-001.json":[{"lib":"handlebars.php","test":"fixture\/002-simple-if-001.json","loop":100000,"time":29.73476600647,"match":"CR\/LF"},{"lib":"lightncandy","test":"fixture\/002-simple-if-001.json","loop":100000,"time":2.6470370292664,"match":"YES"},{"lib":"mustache-php","test":"fixture\/002-simple-if-001.json","loop":100000,"time":14.491711139679,"match":"YES"},{"lib":"mustache.php","test":"fixture\/002-simple-if-001.json","loop":100000,"time":8.4071009159088,"match":"CR\/LF"}],"fixture\/002-simple-if-002.json":[{"lib":"handlebars.php","test":"fixture\/002-simple-if-002.json","loop":100000,"time":21.41800403595,"match":"CR\/LF"},{"lib":"lightncandy","test":"fixture\/002-simple-if-002.json","loop":100000,"time":2.2570369243622,"match":"YES"},{"lib":"mustache-php","test":"fixture\/002-simple-if-002.json","loop":100000,"time":9.854798078537,"match":"YES"},{"lib":"mustache.php","test":"fixture\/002-simple-if-002.json","loop":100000,"time":5.759819984436,"match":"CR\/LF"}],"fixture\/002-simple-if-003.json":[{"lib":"handlebars.php","test":"fixture\/002-simple-if-003.json","loop":100000,"time":21.545207977295,"match":"CR\/LF"},{"lib":"lightncandy","test":"fixture\/002-simple-if-003.json","loop":100000,"time":2.636873960495,"match":"YES"},{"lib":"mustache-php","test":"fixture\/002-simple-if-003.json","loop":100000,"time":9.25519490242,"match":"YES"},{"lib":"mustache.php","test":"fixture\/002-simple-if-003.json","loop":100000,"time":5.7237091064453,"match":"CR\/LF"}],"fixture\/003-simple-else-001.json":[{"lib":"handlebars.php","test":"fixture\/003-simple-else-001.json","loop":100000,"time":33.75423002243,"match":"CR\/LF"},{"lib":"lightncandy","test":"fixture\/003-simple-else-001.json","loop":100000,"time":2.7831158638,"match":"YES"},{"lib":"mustache-php","test":"fixture\/003-simple-else-001.json","loop":100000,"time":17.17378282547,"match":"YES"},{"lib":"mustache.php","test":"fixture\/003-simple-else-001.json","loop":100000,"time":9.4256460666656,"match":"CR\/LF"}],"fixture\/003-simple-else-002.json":[{"lib":"handlebars.php","test":"fixture\/003-simple-else-002.json","loop":100000,"time":34.113007068634,"match":"CR\/LF"},{"lib":"lightncandy","test":"fixture\/003-simple-else-002.json","loop":100000,"time":0,"match":"OUTPUT"},{"lib":"mustache-php","test":"fixture\/003-simple-else-002.json","loop":100000,"time":16.895195007324,"match":"YES"},{"lib":"mustache.php","test":"fixture\/003-simple-else-002.json","loop":100000,"time":8.0287301540375,"match":"CR\/LF"}],"fixture\/003-simple-else-003.json":[{"lib":"handlebars.php","test":"fixture\/003-simple-else-003.json","loop":100000,"time":34.399478912354,"match":"CR\/LF"},{"lib":"lightncandy","test":"fixture\/003-simple-else-003.json","loop":100000,"time":3.6509549617767,"match":"YES"},{"lib":"mustache-php","test":"fixture\/003-simple-else-003.json","loop":100000,"time":15.966216802597,"match":"YES"},{"lib":"mustache.php","test":"fixture\/003-simple-else-003.json","loop":100000,"time":7.8779668807983,"match":"CR\/LF"}],"fixture\/003-simple-else-004.json":[{"lib":"handlebars.php","test":"fixture\/003-simple-else-004.json","loop":100000,"time":0,"match":"OUTPUT"},{"lib":"lightncandy","test":"fixture\/003-simple-else-004.json","loop":100000,"time":2.8550419807434,"match":"YES"},{"lib":"mustache-php","test":"fixture\/003-simple-else-004.json","loop":100000,"time":0,"match":"OUTPUT"},{"lib":"mustache.php","test":"fixture\/003-simple-else-004.json","loop":100000,"time":0,"match":"OUTPUT"}],"fixture\/003-simple-else-005.json":[{"lib":"handlebars.php","test":"fixture\/003-simple-else-005.json","loop":100000,"time":0,"match":"OUTPUT"},{"lib":"lightncandy","test":"fixture\/003-simple-else-005.json","loop":100000,"time":2.8646910190582,"match":"YES"},{"lib":"mustache-php","test":"fixture\/003-simple-else-005.json","loop":100000,"time":0,"match":"OUTPUT"},{"lib":"mustache.php","test":"fixture\/003-simple-else-005.json","loop":100000,"time":0,"match":"OUTPUT"}],"fixture\/003-simple-else-006.json":[{"lib":"handlebars.php","test":"fixture\/003-simple-else-006.json","loop":100000,"time":0,"match":"OUTPUT"},{"lib":"lightncandy","test":"fixture\/003-simple-else-006.json","loop":100000,"time":3.1143329143524,"match":"YES"},{"lib":"mustache-php","test":"fixture\/003-simple-else-006.json","loop":100000,"time":0,"match":"OUTPUT"},{"lib":"mustache.php","test":"fixture\/003-simple-else-006.json","loop":100000,"time":0,"match":"OUTPUT"}],"fixture\/003-simple-else-007.json":[{"lib":"handlebars.php","test":"fixture\/003-simple-else-007.json","loop":100000,"time":0,"match":"OUTPUT"},{"lib":"lightncandy","test":"fixture\/003-simple-else-007.json","loop":100000,"time":3.1123330593109,"match":"YES"},{"lib":"mustache-php","test":"fixture\/003-simple-else-007.json","loop":100000,"time":0,"match":"OUTPUT"},{"lib":"mustache.php","test":"fixture\/003-simple-else-007.json","loop":100000,"time":0,"match":"OUTPUT"}],"fixture\/003-simple-else-008.json":[{"lib":"handlebars.php","test":"fixture\/003-simple-else-008.json","loop":100000,"time":0,"match":"OUTPUT"},{"lib":"lightncandy","test":"fixture\/003-simple-else-008.json","loop":100000,"time":3.1066310405731,"match":"YES"},{"lib":"mustache-php","test":"fixture\/003-simple-else-008.json","loop":100000,"time":0,"match":"OUTPUT"},{"lib":"mustache.php","test":"fixture\/003-simple-else-008.json","loop":100000,"time":0,"match":"OUTPUT"}],"fixture\/003-simple-else-009.json":[{"lib":"handlebars.php","test":"fixture\/003-simple-else-009.json","loop":100000,"time":33.863855838776,"match":"CR\/LF"},{"lib":"lightncandy","test":"fixture\/003-simple-else-009.json","loop":100000,"time":2.7152090072632,"match":"YES"},{"lib":"mustache-php","test":"fixture\/003-simple-else-009.json","loop":100000,"time":17.03718495369,"match":"YES"},{"lib":"mustache.php","test":"fixture\/003-simple-else-009.json","loop":100000,"time":8.045581817627,"match":"CR\/LF"}],"fixture\/003-simple-else-010.json":[{"lib":"handlebars.php","test":"fixture\/003-simple-else-010.json","loop":100000,"time":0,"match":"OUTPUT"},{"lib":"lightncandy","test":"fixture\/003-simple-else-010.json","loop":100000,"time":2.8706691265106,"match":"YES"},{"lib":"mustache-php","test":"fixture\/003-simple-else-010.json","loop":100000,"time":0,"match":"OUTPUT"},{"lib":"mustache.php","test":"fixture\/003-simple-else-010.json","loop":100000,"time":0,"match":"OUTPUT"}],"fixture\/003-simple-else-011.json":[{"lib":"handlebars.php","test":"fixture\/003-simple-else-011.json","loop":100000,"time":0,"match":"OUTPUT"},{"lib":"lightncandy","test":"fixture\/003-simple-else-011.json","loop":100000,"time":3.104907989502,"match":"YES"},{"lib":"mustache-php","test":"fixture\/003-simple-else-011.json","loop":100000,"time":0,"match":"OUTPUT"},{"lib":"mustache.php","test":"fixture\/003-simple-else-011.json","loop":100000,"time":0,"match":"OUTPUT"}],"fixture\/003-simple-else-012.json":[{"lib":"handlebars.php","test":"fixture\/003-simple-else-012.json","loop":100000,"time":0,"match":"OUTPUT"},{"lib":"lightncandy","test":"fixture\/003-simple-else-012.json","loop":100000,"time":3.4137978553772,"match":"YES"},{"lib":"mustache-php","test":"fixture\/003-simple-else-012.json","loop":100000,"time":0,"match":"OUTPUT"},{"lib":"mustache.php","test":"fixture\/003-simple-else-012.json","loop":100000,"time":0,"match":"OUTPUT"}],"fixture\/004-simple-mvars-001.json":[{"lib":"handlebars.php","test":"fixture\/004-simple-mvars-001.json","loop":100000,"time":148.55368089676,"match":"YES"},{"lib":"lightncandy","test":"fixture\/004-simple-mvars-001.json","loop":100000,"time":5.6346499919891,"match":"YES"},{"lib":"mustache-php","test":"fixture\/004-simple-mvars-001.json","loop":100000,"time":60.976880073547,"match":"YES"},{"lib":"mustache.php","test":"fixture\/004-simple-mvars-001.json","loop":100000,"time":30.105960845947,"match":"YES"}],"fixture\/004-simple-mvars-002.json":[{"lib":"handlebars.php","test":"fixture\/004-simple-mvars-002.json","loop":100000,"time":148.23787307739,"match":"YES"},{"lib":"lightncandy","test":"fixture\/004-simple-mvars-002.json","loop":100000,"time":5.67120885849,"match":"YES"},{"lib":"mustache-php","test":"fixture\/004-simple-mvars-002.json","loop":100000,"time":60.72842502594,"match":"YES"},{"lib":"mustache.php","test":"fixture\/004-simple-mvars-002.json","loop":100000,"time":30.738445997238,"match":"YES"}],"fixture\/004-simple-mvars-003.json":[{"lib":"handlebars.php","test":"fixture\/004-simple-mvars-003.json","loop":100000,"time":143.0884809494,"match":"YES"},{"lib":"lightncandy","test":"fixture\/004-simple-mvars-003.json","loop":100000,"time":6.7426581382751,"match":"YES"},{"lib":"mustache-php","test":"fixture\/004-simple-mvars-003.json","loop":100000,"time":51.922420024872,"match":"YES"},{"lib":"mustache.php","test":"fixture\/004-simple-mvars-003.json","loop":100000,"time":15.536197900772,"match":"YES"}],"fixture\/004-simple-mvars-004.json":[{"lib":"handlebars.php","test":"fixture\/004-simple-mvars-004.json","loop":100000,"time":149.13936805725,"match":"YES"},{"lib":"lightncandy","test":"fixture\/004-simple-mvars-004.json","loop":100000,"time":6.1626060009003,"match":"YES"},{"lib":"mustache-php","test":"fixture\/004-simple-mvars-004.json","loop":100000,"time":60.5387570858,"match":"YES"},{"lib":"mustache.php","test":"fixture\/004-simple-mvars-004.json","loop":100000,"time":29.870540857315,"match":"YES"}],"fixture\/005-simple-escape-001.json":[{"lib":"handlebars.php","test":"fixture\/005-simple-escape-001.json","loop":100000,"time":0,"match":"OUTPUT"},{"lib":"lightncandy","test":"fixture\/005-simple-escape-001.json","loop":100000,"time":1.1101670265198,"match":"YES"},{"lib":"mustache-php","test":"fixture\/005-simple-escape-001.json","loop":100000,"time":0,"match":"OUTPUT"},{"lib":"mustache.php","test":"fixture\/005-simple-escape-001.json","loop":100000,"time":0,"match":"OUTPUT"}],"fixture\/005-simple-escape-002.json":[{"lib":"handlebars.php","test":"fixture\/005-simple-escape-002.json","loop":100000,"time":0,"match":"OUTPUT"},{"lib":"lightncandy","test":"fixture\/005-simple-escape-002.json","loop":100000,"time":1.0970301628113,"match":"YES"},{"lib":"mustache-php","test":"fixture\/005-simple-escape-002.json","loop":100000,"time":0,"match":"OUTPUT"},{"lib":"mustache.php","test":"fixture\/005-simple-escape-002.json","loop":100000,"time":0,"match":"OUTPUT"}],"fixture\/005-simple-escape-003.json":[{"lib":"handlebars.php","test":"fixture\/005-simple-escape-003.json","loop":100000,"time":0,"match":"OUTPUT"},{"lib":"lightncandy","test":"fixture\/005-simple-escape-003.json","loop":100000,"time":1.2286419868469,"match":"QUOTE"},{"lib":"mustache-php","test":"fixture\/005-simple-escape-003.json","loop":100000,"time":0,"match":"OUTPUT"},{"lib":"mustache.php","test":"fixture\/005-simple-escape-003.json","loop":100000,"time":0,"match":"OUTPUT"}],"fixture\/006-simple-section-001.json":[{"lib":"handlebars.php","test":"fixture\/006-simple-section-001.json","loop":100000,"time":59.128355979919,"match":"CR\/LF"},{"lib":"lightncandy","test":"fixture\/006-simple-section-001.json","loop":100000,"time":5.8524777889252,"match":"YES"},{"lib":"mustache-php","test":"fixture\/006-simple-section-001.json","loop":100000,"time":26.58989906311,"match":"YES"},{"lib":"mustache.php","test":"fixture\/006-simple-section-001.json","loop":100000,"time":14.040349960327,"match":"CR\/LF"}],"fixture\/006-simple-section-002.json":[{"lib":"handlebars.php","test":"fixture\/006-simple-section-002.json","loop":100000,"time":29.769820928574,"match":"CR\/LF"},{"lib":"lightncandy","test":"fixture\/006-simple-section-002.json","loop":100000,"time":3.0773718357086,"match":"YES"},{"lib":"mustache-php","test":"fixture\/006-simple-section-002.json","loop":100000,"time":11.512040138245,"match":"YES"},{"lib":"mustache.php","test":"fixture\/006-simple-section-002.json","loop":100000,"time":6.9606909751892,"match":"CR\/LF"}],"fixture\/006-simple-section-003.json":[{"lib":"handlebars.php","test":"fixture\/006-simple-section-003.json","loop":100000,"time":0,"match":"OUTPUT"},{"lib":"lightncandy","test":"fixture\/006-simple-section-003.json","loop":100000,"time":3.3758411407471,"match":"YES"},{"lib":"mustache-php","test":"fixture\/006-simple-section-003.json","loop":100000,"time":0,"match":"OUTPUT"},{"lib":"mustache.php","test":"fixture\/006-simple-section-003.json","loop":100000,"time":0,"match":"OUTPUT"}],"fixture\/006-simple-section-004.json":[{"lib":"handlebars.php","test":"fixture\/006-simple-section-004.json","loop":100000,"time":0,"match":"OUTPUT"},{"lib":"lightncandy","test":"fixture\/006-simple-section-004.json","loop":100000,"time":3.3289759159088,"match":"YES"},{"lib":"mustache-php","test":"fixture\/006-simple-section-004.json","loop":100000,"time":0,"match":"OUTPUT"},{"lib":"mustache.php","test":"fixture\/006-simple-section-004.json","loop":100000,"time":0,"match":"OUTPUT"}],"fixture\/006-simple-section-005.json":[{"lib":"handlebars.php","test":"fixture\/006-simple-section-005.json","loop":100000,"time":29.24794793129,"match":"CR\/LF"},{"lib":"lightncandy","test":"fixture\/006-simple-section-005.json","loop":100000,"time":2.7891409397125,"match":"YES"},{"lib":"mustache-php","test":"fixture\/006-simple-section-005.json","loop":100000,"time":12.299506902695,"match":"YES"},{"lib":"mustache.php","test":"fixture\/006-simple-section-005.json","loop":100000,"time":7.0471489429474,"match":"CR\/LF"}],"fixture\/006-simple-section-006.json":[{"lib":"handlebars.php","test":"fixture\/006-simple-section-006.json","loop":100000,"time":43.324634075165,"match":"CR\/LF"},{"lib":"lightncandy","test":"fixture\/006-simple-section-006.json","loop":100000,"time":3.3178489208221,"match":"YES"},{"lib":"mustache-php","test":"fixture\/006-simple-section-006.json","loop":100000,"time":19.032212972641,"match":"YES"},{"lib":"mustache.php","test":"fixture\/006-simple-section-006.json","loop":100000,"time":10.943045854568,"match":"CR\/LF"}],"fixture\/006-simple-section-007.json":[{"lib":"handlebars.php","test":"fixture\/006-simple-section-007.json","loop":100000,"time":58.538573026657,"match":"CR\/LF"},{"lib":"lightncandy","test":"fixture\/006-simple-section-007.json","loop":100000,"time":5.1005551815033,"match":"YES"},{"lib":"mustache-php","test":"fixture\/006-simple-section-007.json","loop":100000,"time":26.565788984299,"match":"YES"},{"lib":"mustache.php","test":"fixture\/006-simple-section-007.json","loop":100000,"time":14.407120943069,"match":"CR\/LF"}],"fixture\/006-simple-section-008.json":[{"lib":"handlebars.php","test":"fixture\/006-simple-section-008.json","loop":100000,"time":74.295855998993,"match":"CR\/LF"},{"lib":"lightncandy","test":"fixture\/006-simple-section-008.json","loop":100000,"time":5.6243238449097,"match":"YES"},{"lib":"mustache-php","test":"fixture\/006-simple-section-008.json","loop":100000,"time":32.487474918365,"match":"YES"},{"lib":"mustache.php","test":"fixture\/006-simple-section-008.json","loop":100000,"time":17.136090993881,"match":"CR\/LF"}],"fixture\/006-simple-section-009.json":[{"lib":"handlebars.php","test":"fixture\/006-simple-section-009.json","loop":100000,"time":0,"match":"OUTPUT"},{"lib":"lightncandy","test":"fixture\/006-simple-section-009.json","loop":100000,"time":0,"match":"OUTPUT"},{"lib":"mustache-php","test":"fixture\/006-simple-section-009.json","loop":100000,"time":0,"match":"OUTPUT"},{"lib":"mustache.php","test":"fixture\/006-simple-section-009.json","loop":100000,"time":0,"match":"OUTPUT"}],"fixture\/007-simple-sections-001.json":[{"lib":"handlebars.php","test":"fixture\/007-simple-sections-001.json","loop":100000,"time":93.287281036377,"match":"CR\/LF"},{"lib":"lightncandy","test":"fixture\/007-simple-sections-001.json","loop":100000,"time":0,"match":"OUTPUT"},{"lib":"mustache-php","test":"fixture\/007-simple-sections-001.json","loop":100000,"time":55.172532081604,"match":"YES"},{"lib":"mustache.php","test":"fixture\/007-simple-sections-001.json","loop":100000,"time":25.436980962753,"match":"CR\/LF"}],"fixture\/007-simple-sections-002.json":[{"lib":"handlebars.php","test":"fixture\/007-simple-sections-002.json","loop":100000,"time":51.946703910828,"match":"CR\/LF"},{"lib":"lightncandy","test":"fixture\/007-simple-sections-002.json","loop":100000,"time":0,"match":"OUTPUT"},{"lib":"mustache-php","test":"fixture\/007-simple-sections-002.json","loop":100000,"time":29.321012973785,"match":"YES"},{"lib":"mustache.php","test":"fixture\/007-simple-sections-002.json","loop":100000,"time":14.292671918869,"match":"CR\/LF"}],"fixture\/007-simple-sections-003.json":[{"lib":"handlebars.php","test":"fixture\/007-simple-sections-003.json","loop":100000,"time":93.444444894791,"match":"CR\/LF"},{"lib":"lightncandy","test":"fixture\/007-simple-sections-003.json","loop":100000,"time":0,"match":"OUTPUT"},{"lib":"mustache-php","test":"fixture\/007-simple-sections-003.json","loop":100000,"time":54.733572006226,"match":"YES"},{"lib":"mustache.php","test":"fixture\/007-simple-sections-003.json","loop":100000,"time":25.451951026917,"match":"CR\/LF"}],"fixture\/007-simple-sections-004.json":[{"lib":"handlebars.php","test":"fixture\/007-simple-sections-004.json","loop":100000,"time":20.936155080795,"match":"CR\/LF"},{"lib":"lightncandy","test":"fixture\/007-simple-sections-004.json","loop":100000,"time":2.8508150577545,"match":"YES"},{"lib":"mustache-php","test":"fixture\/007-simple-sections-004.json","loop":100000,"time":10.841688156128,"match":"YES"},{"lib":"mustache.php","test":"fixture\/007-simple-sections-004.json","loop":100000,"time":6.7847311496735,"match":"CR\/LF"}],"fixture\/008-simple-comment-001.json":[{"lib":"handlebars.php","test":"fixture\/008-simple-comment-001.json","loop":100000,"time":20.099272012711,"match":"CR\/LF"},{"lib":"lightncandy","test":"fixture\/008-simple-comment-001.json","loop":100000,"time":2.6480898857117,"match":"YES"},{"lib":"mustache-php","test":"fixture\/008-simple-comment-001.json","loop":100000,"time":9.3187680244446,"match":"YES"},{"lib":"mustache.php","test":"fixture\/008-simple-comment-001.json","loop":100000,"time":5.5816750526428,"match":"CR\/LF"}],"fixture\/008-simple-comment-002.json":[{"lib":"handlebars.php","test":"fixture\/008-simple-comment-002.json","loop":100000,"time":28.457327842712,"match":"CR\/LF"},{"lib":"lightncandy","test":"fixture\/008-simple-comment-002.json","loop":100000,"time":3.0543820858002,"match":"YES"},{"lib":"mustache-php","test":"fixture\/008-simple-comment-002.json","loop":100000,"time":14.047627210617,"match":"YES"},{"lib":"mustache.php","test":"fixture\/008-simple-comment-002.json","loop":100000,"time":8.3055889606476,"match":"CR\/LF"}],"fixture\/009-simple-dot-001.json":[{"lib":"handlebars.php","test":"fixture\/009-simple-dot-001.json","loop":100000,"time":47.504302024841,"match":"SINGLEQUOTE"},{"lib":"lightncandy","test":"fixture\/009-simple-dot-001.json","loop":100000,"time":2.2142889499664,"match":"QUOTE"},{"lib":"mustache-php","test":"fixture\/009-simple-dot-001.json","loop":100000,"time":0,"match":"OUTPUT"},{"lib":"mustache.php","test":"fixture\/009-simple-dot-001.json","loop":100000,"time":21.235466957092,"match":"SINGLEQUOTE"}],"fixture\/009-simple-dot-002.json":[{"lib":"handlebars.php","test":"fixture\/009-simple-dot-002.json","loop":100000,"time":42.905683994293,"match":"YES"},{"lib":"lightncandy","test":"fixture\/009-simple-dot-002.json","loop":100000,"time":2.3964881896973,"match":"YES"},{"lib":"mustache-php","test":"fixture\/009-simple-dot-002.json","loop":100000,"time":0,"match":"OUTPUT"},{"lib":"mustache.php","test":"fixture\/009-simple-dot-002.json","loop":100000,"time":11.057023048401,"match":"YES"}],"fixture\/009-simple-dot-003.json":[{"lib":"handlebars.php","test":"fixture\/009-simple-dot-003.json","loop":100000,"time":45.748000144958,"match":"YES"},{"lib":"lightncandy","test":"fixture\/009-simple-dot-003.json","loop":100000,"time":1.7886099815369,"match":"YES"},{"lib":"mustache-php","test":"fixture\/009-simple-dot-003.json","loop":100000,"time":0,"match":"OUTPUT"},{"lib":"mustache.php","test":"fixture\/009-simple-dot-003.json","loop":100000,"time":18.6258289814,"match":"YES"}],"fixture\/010-simple-doublesection-001.json":[{"lib":"handlebars.php","test":"fixture\/010-simple-doublesection-001.json","loop":100000,"time":0,"match":"OUTPUT"},{"lib":"lightncandy","test":"fixture\/010-simple-doublesection-001.json","loop":100000,"time":8.2686579227448,"match":"YES"},{"lib":"mustache-php","test":"fixture\/010-simple-doublesection-001.json","loop":100000,"time":29.346999883652,"match":"YES"},{"lib":"mustache.php","test":"fixture\/010-simple-doublesection-001.json","loop":100000,"time":0,"match":"OUTPUT"}],"fixture\/010-simple-doublesection-002.json":[{"lib":"handlebars.php","test":"fixture\/010-simple-doublesection-002.json","loop":100000,"time":0,"match":"OUTPUT"},{"lib":"lightncandy","test":"fixture\/010-simple-doublesection-002.json","loop":100000,"time":0,"match":"OUTPUT"},{"lib":"mustache-php","test":"fixture\/010-simple-doublesection-002.json","loop":100000,"time":0,"match":"OUTPUT"},{"lib":"mustache.php","test":"fixture\/010-simple-doublesection-002.json","loop":100000,"time":0,"match":"OUTPUT"}],"fixture\/010-simple-doublesection-003.json":[null,{"lib":"lightncandy","test":"fixture\/010-simple-doublesection-003.json","loop":100000,"time":0,"match":"OUTPUT"},{"lib":"mustache-php","test":"fixture\/010-simple-doublesection-003.json","loop":100000,"time":0,"match":"OUTPUT"},{"lib":"mustache.php","test":"fixture\/010-simple-doublesection-003.json","loop":100000,"time":0,"match":"OUTPUT"}],"fixture\/010-simple-doublesection-004.json":[{"lib":"handlebars.php","test":"fixture\/010-simple-doublesection-004.json","loop":100000,"time":0,"match":"OUTPUT"},{"lib":"lightncandy","test":"fixture\/010-simple-doublesection-004.json","loop":100000,"time":0,"match":"OUTPUT"},{"lib":"mustache-php","test":"fixture\/010-simple-doublesection-004.json","loop":100000,"time":0,"match":"OUTPUT"},{"lib":"mustache.php","test":"fixture\/010-simple-doublesection-004.json","loop":100000,"time":0,"match":"OUTPUT"}],"fixture\/010-simple-doublesection-005.json":[{"lib":"handlebars.php","test":"fixture\/010-simple-doublesection-005.json","loop":100000,"time":0,"match":"OUTPUT"},{"lib":"lightncandy","test":"fixture\/010-simple-doublesection-005.json","loop":100000,"time":0,"match":"OUTPUT"},{"lib":"mustache-php","test":"fixture\/010-simple-doublesection-005.json","loop":100000,"time":0,"match":"OUTPUT"},{"lib":"mustache.php","test":"fixture\/010-simple-doublesection-005.json","loop":100000,"time":0,"match":"OUTPUT"}],"fixture\/011-simple-context-001.json":[{"lib":"handlebars.php","test":"fixture\/011-simple-context-001.json","loop":100000,"time":0,"match":"OUTPUT"},{"lib":"lightncandy","test":"fixture\/011-simple-context-001.json","loop":100000,"time":12.829764127731,"match":"YES"},{"lib":"mustache-php","test":"fixture\/011-simple-context-001.json","loop":100000,"time":0,"match":"OUTPUT"},{"lib":"mustache.php","test":"fixture\/011-simple-context-001.json","loop":100000,"time":0,"match":"OUTPUT"}],"fixture\/011-simple-context-002.json":[{"lib":"handlebars.php","test":"fixture\/011-simple-context-002.json","loop":100000,"time":0,"match":"OUTPUT"},{"lib":"lightncandy","test":"fixture\/011-simple-context-002.json","loop":100000,"time":12.617038965225,"match":"YES"},{"lib":"mustache-php","test":"fixture\/011-simple-context-002.json","loop":100000,"time":0,"match":"OUTPUT"},{"lib":"mustache.php","test":"fixture\/011-simple-context-002.json","loop":100000,"time":0,"match":"OUTPUT"}],"fixture\/012-simple-this-001.json":[{"lib":"handlebars.php","test":"fixture\/012-simple-this-001.json","loop":100000,"time":0,"match":"OUTPUT"},{"lib":"lightncandy","test":"fixture\/012-simple-this-001.json","loop":100000,"time":0,"match":"OUTPUT"},{"lib":"mustache-php","test":"fixture\/012-simple-this-001.json","loop":100000,"time":0,"match":"OUTPUT"},{"lib":"mustache.php","test":"fixture\/012-simple-this-001.json","loop":100000,"time":0,"match":"OUTPUT"}],"fixture\/012-simple-this-002.json":[{"lib":"handlebars.php","test":"fixture\/012-simple-this-002.json","loop":100000,"time":0,"match":"OUTPUT"},{"lib":"lightncandy","test":"fixture\/012-simple-this-002.json","loop":100000,"time":0,"match":"OUTPUT"},{"lib":"mustache-php","test":"fixture\/012-simple-this-002.json","loop":100000,"time":0,"match":"OUTPUT"},{"lib":"mustache.php","test":"fixture\/012-simple-this-002.json","loop":100000,"time":0,"match":"OUTPUT"}],"fixture\/012-simple-this-003.json":[{"lib":"handlebars.php","test":"fixture\/012-simple-this-003.json","loop":100000,"time":0,"match":"OUTPUT"},null,{"lib":"mustache-php","test":"fixture\/012-simple-this-003.json","loop":100000,"time":0,"match":"OUTPUT"},{"lib":"mustache.php","test":"fixture\/012-simple-this-003.json","loop":100000,"time":0,"match":"OUTPUT"}],"fixture\/012-simple-this-004.json":[{"lib":"handlebars.php","test":"fixture\/012-simple-this-004.json","loop":100000,"time":0,"match":"OUTPUT"},null,{"lib":"mustache-php","test":"fixture\/012-simple-this-004.json","loop":100000,"time":0,"match":"OUTPUT"},{"lib":"mustache.php","test":"fixture\/012-simple-this-004.json","loop":100000,"time":0,"match":"OUTPUT"}],"fixture\/012-simple-this-005.json":[{"lib":"handlebars.php","test":"fixture\/012-simple-this-005.json","loop":100000,"time":0,"match":"OUTPUT"},null,{"lib":"mustache-php","test":"fixture\/012-simple-this-005.json","loop":100000,"time":0,"match":"OUTPUT"},{"lib":"mustache.php","test":"fixture\/012-simple-this-005.json","loop":100000,"time":0,"match":"OUTPUT"}],"fixture\/012-simple-this-006.json":[{"lib":"handlebars.php","test":"fixture\/012-simple-this-006.json","loop":100000,"time":0,"match":"OUTPUT"},null,{"lib":"mustache-php","test":"fixture\/012-simple-this-006.json","loop":100000,"time":0,"match":"OUTPUT"},{"lib":"mustache.php","test":"fixture\/012-simple-this-006.json","loop":100000,"time":0,"match":"OUTPUT"}],"fixture\/013-hb-each-001.json":[{"lib":"handlebars.php","test":"fixture\/013-hb-each-001.json","loop":100000,"time":60.797459125519,"match":"CR\/LF"},{"lib":"lightncandy","test":"fixture\/013-hb-each-001.json","loop":100000,"time":3.966717004776,"match":"YES"},null,null],"fixture\/013-hb-each-002.json":[{"lib":"handlebars.php","test":"fixture\/013-hb-each-002.json","loop":100000,"time":30.916350126266,"match":"CR\/LF"},{"lib":"lightncandy","test":"fixture\/013-hb-each-002.json","loop":100000,"time":2.7490410804749,"match":"YES"},null,null],"fixture\/013-hb-each-003.json":[{"lib":"handlebars.php","test":"fixture\/013-hb-each-003.json","loop":100000,"time":30.737668037415,"match":"CR\/LF"},{"lib":"lightncandy","test":"fixture\/013-hb-each-003.json","loop":100000,"time":2.6707758903503,"match":"YES"},null,null],"fixture\/013-hb-each-004.json":[{"lib":"handlebars.php","test":"fixture\/013-hb-each-004.json","loop":100000,"time":31.217340946198,"match":"CR\/LF"},{"lib":"lightncandy","test":"fixture\/013-hb-each-004.json","loop":100000,"time":2.6642079353333,"match":"YES"},null,null],"fixture\/013-hb-each-005.json":[{"lib":"handlebars.php","test":"fixture\/013-hb-each-005.json","loop":100000,"time":30.775908946991,"match":"CR\/LF"},{"lib":"lightncandy","test":"fixture\/013-hb-each-005.json","loop":100000,"time":3.064551115036,"match":"YES"},null,null],"fixture\/013-hb-each-006.json":[{"lib":"handlebars.php","test":"fixture\/013-hb-each-006.json","loop":100000,"time":30.559730052948,"match":"CR\/LF"},{"lib":"lightncandy","test":"fixture\/013-hb-each-006.json","loop":100000,"time":2.676342010498,"match":"YES"},null,null],"fixture\/013-hb-each-007.json":[{"lib":"handlebars.php","test":"fixture\/013-hb-each-007.json","loop":100000,"time":61.238026857376,"match":"CR\/LF"},{"lib":"lightncandy","test":"fixture\/013-hb-each-007.json","loop":100000,"time":4.4497139453888,"match":"YES"},null,null],"fixture\/013-hb-each-008.json":[{"lib":"handlebars.php","test":"fixture\/013-hb-each-008.json","loop":100000,"time":75.47068977356,"match":"CR\/LF"},{"lib":"lightncandy","test":"fixture\/013-hb-each-008.json","loop":100000,"time":5.3740508556366,"match":"YES"},null,null],"fixture\/013-hb-each-009.json":[{"lib":"handlebars.php","test":"fixture\/013-hb-each-009.json","loop":100000,"time":0,"match":"OUTPUT"},{"lib":"lightncandy","test":"fixture\/013-hb-each-009.json","loop":100000,"time":0,"match":"OUTPUT"},null,null],"fixture\/014-hb-if-001.json":[{"lib":"handlebars.php","test":"fixture\/014-hb-if-001.json","loop":100000,"time":55.454473972321,"match":"CR\/LF"},{"lib":"lightncandy","test":"fixture\/014-hb-if-001.json","loop":100000,"time":3.2878677845001,"match":"YES"},null,null],"fixture\/014-hb-if-002.json":[{"lib":"handlebars.php","test":"fixture\/014-hb-if-002.json","loop":100000,"time":65.818007946014,"match":"CR\/LF"},{"lib":"lightncandy","test":"fixture\/014-hb-if-002.json","loop":100000,"time":2.9858379364014,"match":"YES"},null,null],"fixture\/014-hb-if-003.json":[{"lib":"handlebars.php","test":"fixture\/014-hb-if-003.json","loop":100000,"time":66.687813997269,"match":"CR\/LF"},{"lib":"lightncandy","test":"fixture\/014-hb-if-003.json","loop":100000,"time":2.9900541305542,"match":"YES"},null,null]}}